Strana/__init__.py
Strana/builtin.py
Strana/context.py
Strana/engine.py
Strana/exception.py
Strana/library.py
Strana/node.py
Strana/template.py
Strana-0.0.3.dist-info/LICENSE.txt
Strana-0.0.3.dist-info/METADATA
Strana-0.0.3.dist-info/WHEEL
Strana-0.0.3.dist-info/top_level.txt
Strana-0.0.3.dist-info/RECORD
