Metadata-Version: 2.1
Name: Strana
Version: 0.0.3
Summary: Strana is a templating engine inspired by Jinja2
Home-page: https://github.com/i-abh-esc-wq/Strana
Author: Aniket Bhattacharyea
Author-email: i_abh_esc_wq@protonmail.com
License: GNU General Public License v3
Keywords: templating engine
Platform: UNKNOWN
Classifier: Development Status :: 4 - Beta
Classifier: Intended Audience :: Developers
Classifier: License :: OSI Approved :: GNU General Public License v3 (GPLv3)
Requires-Python: >=3
